{
    "metadata": {
        "season_year": 2025,
        "week_num": 11,
        "date": "2025-07-08 16:00:00"
    },
    "data": [
        {
            "display_name": "\u0392LIND",
            "player_id": 0.0,
            "hole_score_1": 99999.0,
            "hole_score_2": 99999.0,
            "hole_score_3": 99999.0,
            "hole_score_4": 99999.0,
            "hole_score_5": 99999.0,
            "hole_score_6": 99999.0,
            "hole_score_7": 99999.0,
            "hole_score_8": 99999.0,
            "hole_score_9": 99999.0,
            "order_num": 1.0,
            "spreadsheet_row_num": 8.0,
            "sex": 99998.0,
            "team_num": 1,
            "tee": 99998.0,
            "captain": 99998.0,
            "hole_scores_array": [
                0,
                0,
                0,
                0,
                0,
                0,
                0,
                0,
                0
            ],
            "net_score": 1.0,
            "hole_score_par_delta_array": [
                0,
                0,
                0,
                0,
                0,
                0,
                0,
                0,
                0
            ],
            "event_info": {
                "event": "None",
                "hole": 0,
                "display_name": ""
            },
            "rank": "",
            "rank_text": 99998,
            "gross_score": 99999.0,
            "round_index": 99999.0
        },
        {
            "display_name": "\u0392LIND",
            "player_id": 0.0,
            "hole_score_1": 99999.0,
            "hole_score_2": 99999.0,
            "hole_score_3": 99999.0,
            "hole_score_4": 99999.0,
            "hole_score_5": 99999.0,
            "hole_score_6": 99999.0,
            "hole_score_7": 99999.0,
            "hole_score_8": 99999.0,
            "hole_score_9": 99999.0,
            "order_num": 2.0,
            "spreadsheet_row_num": 9.0,
            "sex": 99998.0,
            "team_num": 1,
            "tee": 99998.0,
            "captain": 99998.0,
            "hole_scores_array": [
                0,
                0,
                0,
                0,
                0,
                0,
                0,
                0,
                0
            ],
            "net_score": 1.0,
            "hole_score_par_delta_array": [
                0,
                0,
                0,
                0,
                0,
                0,
                0,
                0,
                0
            ],
            "event_info": {
                "event": "None",
                "hole": 0,
                "display_name": ""
            },
            "rank": "",
            "rank_text": 99998,
            "gross_score": 99999.0,
            "round_index": 99999.0
        },
        {
            "display_name": "\u0392LIND",
            "player_id": 0.0,
            "hole_score_1": 99999.0,
            "hole_score_2": 99999.0,
            "hole_score_3": 99999.0,
            "hole_score_4": 99999.0,
            "hole_score_5": 99999.0,
            "hole_score_6": 99999.0,
            "hole_score_7": 99999.0,
            "hole_score_8": 99999.0,
            "hole_score_9": 99999.0,
            "order_num": 3.0,
            "spreadsheet_row_num": 10.0,
            "sex": 99998.0,
            "team_num": 1,
            "tee": 99998.0,
            "captain": 99998.0,
            "hole_scores_array": [
                0,
                0,
                0,
                0,
                0,
                0,
                0,
                0,
                0
            ],
            "net_score": 1.0,
            "hole_score_par_delta_array": [
                0,
                0,
                0,
                0,
                0,
                0,
                0,
                0,
                0
            ],
            "event_info": {
                "event": "None",
                "hole": 0,
                "display_name": ""
            },
            "rank": "",
            "rank_text": 99998,
            "gross_score": 99999.0,
            "round_index": 99999.0
        },
        {
            "display_name": "\u0392LIND",
            "player_id": 0.0,
            "hole_score_1": 99999.0,
            "hole_score_2": 99999.0,
            "hole_score_3": 99999.0,
            "hole_score_4": 99999.0,
            "hole_score_5": 99999.0,
            "hole_score_6": 99999.0,
            "hole_score_7": 99999.0,
            "hole_score_8": 99999.0,
            "hole_score_9": 99999.0,
            "order_num": 4.0,
            "spreadsheet_row_num": 11.0,
            "sex": 99998.0,
            "team_num": 1,
            "tee": 99998.0,
            "captain": 99998.0,
            "hole_scores_array": [
                0,
                0,
                0,
                0,
                0,
                0,
                0,
                0,
                0
            ],
            "net_score": 1.0,
            "hole_score_par_delta_array": [
                0,
                0,
                0,
                0,
                0,
                0,
                0,
                0,
                0
            ],
            "event_info": {
                "event": "None",
                "hole": 0,
                "display_name": ""
            },
            "rank": "",
            "rank_text": 99998,
            "gross_score": 99999.0,
            "round_index": 99999.0
        },
        {
            "display_name": "\u03a4eam 1 Total",
            "player_id": 99998.0,
            "hole_score_1": 99998.0,
            "hole_score_2": 99998.0,
            "hole_score_3": 99998.0,
            "hole_score_4": 99998.0,
            "hole_score_5": 99998.0,
            "hole_score_6": 99998.0,
            "hole_score_7": 99998.0,
            "hole_score_8": 99998.0,
            "hole_score_9": 99998.0,
            "order_num": 99998.0,
            "spreadsheet_row_num": 99998.0,
            "sex": 99998.0,
            "team_num": 1,
            "tee": 99998.0,
            "captain": 99998.0,
            "hole_scores_array": 99998,
            "net_score": 4.0,
            "hole_score_par_delta_array": 99998,
            "event_info": 99998,
            "rank": 1.0,
            "rank_text": "1st",
            "gross_score": 99998.0,
            "round_index": 99998.0
        },
        {
            "display_name": "\u0392LIND",
            "player_id": 0.0,
            "hole_score_1": 99999.0,
            "hole_score_2": 99999.0,
            "hole_score_3": 99999.0,
            "hole_score_4": 99999.0,
            "hole_score_5": 99999.0,
            "hole_score_6": 99999.0,
            "hole_score_7": 99999.0,
            "hole_score_8": 99999.0,
            "hole_score_9": 99999.0,
            "order_num": 5.0,
            "spreadsheet_row_num": 15.0,
            "sex": 99998.0,
            "team_num": 2,
            "tee": 99998.0,
            "captain": 99998.0,
            "hole_scores_array": [
                0,
                0,
                0,
                0,
                0,
                0,
                0,
                0,
                0
            ],
            "net_score": 1.0,
            "hole_score_par_delta_array": [
                0,
                0,
                0,
                0,
                0,
                0,
                0,
                0,
                0
            ],
            "event_info": {
                "event": "None",
                "hole": 0,
                "display_name": ""
            },
            "rank": "",
            "rank_text": 99998,
            "gross_score": 99999.0,
            "round_index": 99999.0
        },
        {
            "display_name": "\u0392LIND",
            "player_id": 0.0,
            "hole_score_1": 99999.0,
            "hole_score_2": 99999.0,
            "hole_score_3": 99999.0,
            "hole_score_4": 99999.0,
            "hole_score_5": 99999.0,
            "hole_score_6": 99999.0,
            "hole_score_7": 99999.0,
            "hole_score_8": 99999.0,
            "hole_score_9": 99999.0,
            "order_num": 6.0,
            "spreadsheet_row_num": 16.0,
            "sex": 99998.0,
            "team_num": 2,
            "tee": 99998.0,
            "captain": 99998.0,
            "hole_scores_array": [
                0,
                0,
                0,
                0,
                0,
                0,
                0,
                0,
                0
            ],
            "net_score": 1.0,
            "hole_score_par_delta_array": [
                0,
                0,
                0,
                0,
                0,
                0,
                0,
                0,
                0
            ],
            "event_info": {
                "event": "None",
                "hole": 0,
                "display_name": ""
            },
            "rank": "",
            "rank_text": 99998,
            "gross_score": 99999.0,
            "round_index": 99999.0
        },
        {
            "display_name": "\u0392LIND",
            "player_id": 0.0,
            "hole_score_1": 99999.0,
            "hole_score_2": 99999.0,
            "hole_score_3": 99999.0,
            "hole_score_4": 99999.0,
            "hole_score_5": 99999.0,
            "hole_score_6": 99999.0,
            "hole_score_7": 99999.0,
            "hole_score_8": 99999.0,
            "hole_score_9": 99999.0,
            "order_num": 7.0,
            "spreadsheet_row_num": 17.0,
            "sex": 99998.0,
            "team_num": 2,
            "tee": 99998.0,
            "captain": 99998.0,
            "hole_scores_array": [
                0,
                0,
                0,
                0,
                0,
                0,
                0,
                0,
                0
            ],
            "net_score": 1.0,
            "hole_score_par_delta_array": [
                0,
                0,
                0,
                0,
                0,
                0,
                0,
                0,
                0
            ],
            "event_info": {
                "event": "None",
                "hole": 0,
                "display_name": ""
            },
            "rank": "",
            "rank_text": 99998,
            "gross_score": 99999.0,
            "round_index": 99999.0
        },
        {
            "display_name": "\u0392LIND",
            "player_id": 0.0,
            "hole_score_1": 99999.0,
            "hole_score_2": 99999.0,
            "hole_score_3": 99999.0,
            "hole_score_4": 99999.0,
            "hole_score_5": 99999.0,
            "hole_score_6": 99999.0,
            "hole_score_7": 99999.0,
            "hole_score_8": 99999.0,
            "hole_score_9": 99999.0,
            "order_num": 8.0,
            "spreadsheet_row_num": 18.0,
            "sex": 99998.0,
            "team_num": 2,
            "tee": 99998.0,
            "captain": 99998.0,
            "hole_scores_array": [
                0,
                0,
                0,
                0,
                0,
                0,
                0,
                0,
                0
            ],
            "net_score": 1.0,
            "hole_score_par_delta_array": [
                0,
                0,
                0,
                0,
                0,
                0,
                0,
                0,
                0
            ],
            "event_info": {
                "event": "None",
                "hole": 0,
                "display_name": ""
            },
            "rank": "",
            "rank_text": 99998,
            "gross_score": 99999.0,
            "round_index": 99999.0
        },
        {
            "display_name": "\u03a4eam 2 Total",
            "player_id": 99998.0,
            "hole_score_1": 99998.0,
            "hole_score_2": 99998.0,
            "hole_score_3": 99998.0,
            "hole_score_4": 99998.0,
            "hole_score_5": 99998.0,
            "hole_score_6": 99998.0,
            "hole_score_7": 99998.0,
            "hole_score_8": 99998.0,
            "hole_score_9": 99998.0,
            "order_num": 99998.0,
            "spreadsheet_row_num": 99998.0,
            "sex": 99998.0,
            "team_num": 2,
            "tee": 99998.0,
            "captain": 99998.0,
            "hole_scores_array": 99998,
            "net_score": 4.0,
            "hole_score_par_delta_array": 99998,
            "event_info": 99998,
            "rank": 1.0,
            "rank_text": "1st",
            "gross_score": 99998.0,
            "round_index": 99998.0
        },
        {
            "display_name": "\u0392LIND",
            "player_id": 0.0,
            "hole_score_1": 99999.0,
            "hole_score_2": 99999.0,
            "hole_score_3": 99999.0,
            "hole_score_4": 99999.0,
            "hole_score_5": 99999.0,
            "hole_score_6": 99999.0,
            "hole_score_7": 99999.0,
            "hole_score_8": 99999.0,
            "hole_score_9": 99999.0,
            "order_num": 9.0,
            "spreadsheet_row_num": 22.0,
            "sex": 99998.0,
            "team_num": 3,
            "tee": 99998.0,
            "captain": 99998.0,
            "hole_scores_array": [
                0,
                0,
                0,
                0,
                0,
                0,
                0,
                0,
                0
            ],
            "net_score": 1.0,
            "hole_score_par_delta_array": [
                0,
                0,
                0,
                0,
                0,
                0,
                0,
                0,
                0
            ],
            "event_info": {
                "event": "None",
                "hole": 0,
                "display_name": ""
            },
            "rank": "",
            "rank_text": 99998,
            "gross_score": 99999.0,
            "round_index": 99999.0
        },
        {
            "display_name": "\u0392LIND",
            "player_id": 0.0,
            "hole_score_1": 99999.0,
            "hole_score_2": 99999.0,
            "hole_score_3": 99999.0,
            "hole_score_4": 99999.0,
            "hole_score_5": 99999.0,
            "hole_score_6": 99999.0,
            "hole_score_7": 99999.0,
            "hole_score_8": 99999.0,
            "hole_score_9": 99999.0,
            "order_num": 10.0,
            "spreadsheet_row_num": 23.0,
            "sex": 99998.0,
            "team_num": 3,
            "tee": 99998.0,
            "captain": 99998.0,
            "hole_scores_array": [
                0,
                0,
                0,
                0,
                0,
                0,
                0,
                0,
                0
            ],
            "net_score": 1.0,
            "hole_score_par_delta_array": [
                0,
                0,
                0,
                0,
                0,
                0,
                0,
                0,
                0
            ],
            "event_info": {
                "event": "None",
                "hole": 0,
                "display_name": ""
            },
            "rank": "",
            "rank_text": 99998,
            "gross_score": 99999.0,
            "round_index": 99999.0
        },
        {
            "display_name": "\u0392LIND",
            "player_id": 0.0,
            "hole_score_1": 99999.0,
            "hole_score_2": 99999.0,
            "hole_score_3": 99999.0,
            "hole_score_4": 99999.0,
            "hole_score_5": 99999.0,
            "hole_score_6": 99999.0,
            "hole_score_7": 99999.0,
            "hole_score_8": 99999.0,
            "hole_score_9": 99999.0,
            "order_num": 11.0,
            "spreadsheet_row_num": 24.0,
            "sex": 99998.0,
            "team_num": 3,
            "tee": 99998.0,
            "captain": 99998.0,
            "hole_scores_array": [
                0,
                0,
                0,
                0,
                0,
                0,
                0,
                0,
                0
            ],
            "net_score": 1.0,
            "hole_score_par_delta_array": [
                0,
                0,
                0,
                0,
                0,
                0,
                0,
                0,
                0
            ],
            "event_info": {
                "event": "None",
                "hole": 0,
                "display_name": ""
            },
            "rank": "",
            "rank_text": 99998,
            "gross_score": 99999.0,
            "round_index": 99999.0
        },
        {
            "display_name": "\u0392LIND",
            "player_id": 0.0,
            "hole_score_1": 99999.0,
            "hole_score_2": 99999.0,
            "hole_score_3": 99999.0,
            "hole_score_4": 99999.0,
            "hole_score_5": 99999.0,
            "hole_score_6": 99999.0,
            "hole_score_7": 99999.0,
            "hole_score_8": 99999.0,
            "hole_score_9": 99999.0,
            "order_num": 12.0,
            "spreadsheet_row_num": 25.0,
            "sex": 99998.0,
            "team_num": 3,
            "tee": 99998.0,
            "captain": 99998.0,
            "hole_scores_array": [
                0,
                0,
                0,
                0,
                0,
                0,
                0,
                0,
                0
            ],
            "net_score": 1.0,
            "hole_score_par_delta_array": [
                0,
                0,
                0,
                0,
                0,
                0,
                0,
                0,
                0
            ],
            "event_info": {
                "event": "None",
                "hole": 0,
                "display_name": ""
            },
            "rank": "",
            "rank_text": 99998,
            "gross_score": 99999.0,
            "round_index": 99999.0
        },
        {
            "display_name": "\u03a4eam 3 Total",
            "player_id": 99998.0,
            "hole_score_1": 99998.0,
            "hole_score_2": 99998.0,
            "hole_score_3": 99998.0,
            "hole_score_4": 99998.0,
            "hole_score_5": 99998.0,
            "hole_score_6": 99998.0,
            "hole_score_7": 99998.0,
            "hole_score_8": 99998.0,
            "hole_score_9": 99998.0,
            "order_num": 99998.0,
            "spreadsheet_row_num": 99998.0,
            "sex": 99998.0,
            "team_num": 3,
            "tee": 99998.0,
            "captain": 99998.0,
            "hole_scores_array": 99998,
            "net_score": 4.0,
            "hole_score_par_delta_array": 99998,
            "event_info": 99998,
            "rank": 1.0,
            "rank_text": "1st",
            "gross_score": 99998.0,
            "round_index": 99998.0
        },
        {
            "display_name": "\u0392LIND",
            "player_id": 0.0,
            "hole_score_1": 99999.0,
            "hole_score_2": 99999.0,
            "hole_score_3": 99999.0,
            "hole_score_4": 99999.0,
            "hole_score_5": 99999.0,
            "hole_score_6": 99999.0,
            "hole_score_7": 99999.0,
            "hole_score_8": 99999.0,
            "hole_score_9": 99999.0,
            "order_num": 13.0,
            "spreadsheet_row_num": 29.0,
            "sex": 99998.0,
            "team_num": 4,
            "tee": 99998.0,
            "captain": 99998.0,
            "hole_scores_array": [
                0,
                0,
                0,
                0,
                0,
                0,
                0,
                0,
                0
            ],
            "net_score": 1.0,
            "hole_score_par_delta_array": [
                0,
                0,
                0,
                0,
                0,
                0,
                0,
                0,
                0
            ],
            "event_info": {
                "event": "None",
                "hole": 0,
                "display_name": ""
            },
            "rank": "",
            "rank_text": 99998,
            "gross_score": 99999.0,
            "round_index": 99999.0
        },
        {
            "display_name": "\u0392LIND",
            "player_id": 0.0,
            "hole_score_1": 99999.0,
            "hole_score_2": 99999.0,
            "hole_score_3": 99999.0,
            "hole_score_4": 99999.0,
            "hole_score_5": 99999.0,
            "hole_score_6": 99999.0,
            "hole_score_7": 99999.0,
            "hole_score_8": 99999.0,
            "hole_score_9": 99999.0,
            "order_num": 14.0,
            "spreadsheet_row_num": 30.0,
            "sex": 99998.0,
            "team_num": 4,
            "tee": 99998.0,
            "captain": 99998.0,
            "hole_scores_array": [
                0,
                0,
                0,
                0,
                0,
                0,
                0,
                0,
                0
            ],
            "net_score": 1.0,
            "hole_score_par_delta_array": [
                0,
                0,
                0,
                0,
                0,
                0,
                0,
                0,
                0
            ],
            "event_info": {
                "event": "None",
                "hole": 0,
                "display_name": ""
            },
            "rank": "",
            "rank_text": 99998,
            "gross_score": 99999.0,
            "round_index": 99999.0
        },
        {
            "display_name": "\u0392LIND",
            "player_id": 0.0,
            "hole_score_1": 99999.0,
            "hole_score_2": 99999.0,
            "hole_score_3": 99999.0,
            "hole_score_4": 99999.0,
            "hole_score_5": 99999.0,
            "hole_score_6": 99999.0,
            "hole_score_7": 99999.0,
            "hole_score_8": 99999.0,
            "hole_score_9": 99999.0,
            "order_num": 15.0,
            "spreadsheet_row_num": 31.0,
            "sex": 99998.0,
            "team_num": 4,
            "tee": 99998.0,
            "captain": 99998.0,
            "hole_scores_array": [
                0,
                0,
                0,
                0,
                0,
                0,
                0,
                0,
                0
            ],
            "net_score": 1.0,
            "hole_score_par_delta_array": [
                0,
                0,
                0,
                0,
                0,
                0,
                0,
                0,
                0
            ],
            "event_info": {
                "event": "None",
                "hole": 0,
                "display_name": ""
            },
            "rank": "",
            "rank_text": 99998,
            "gross_score": 99999.0,
            "round_index": 99999.0
        },
        {
            "display_name": "\u0392LIND",
            "player_id": 0.0,
            "hole_score_1": 99999.0,
            "hole_score_2": 99999.0,
            "hole_score_3": 99999.0,
            "hole_score_4": 99999.0,
            "hole_score_5": 99999.0,
            "hole_score_6": 99999.0,
            "hole_score_7": 99999.0,
            "hole_score_8": 99999.0,
            "hole_score_9": 99999.0,
            "order_num": 16.0,
            "spreadsheet_row_num": 32.0,
            "sex": 99998.0,
            "team_num": 4,
            "tee": 99998.0,
            "captain": 99998.0,
            "hole_scores_array": [
                0,
                0,
                0,
                0,
                0,
                0,
                0,
                0,
                0
            ],
            "net_score": 1.0,
            "hole_score_par_delta_array": [
                0,
                0,
                0,
                0,
                0,
                0,
                0,
                0,
                0
            ],
            "event_info": {
                "event": "None",
                "hole": 0,
                "display_name": ""
            },
            "rank": "",
            "rank_text": 99998,
            "gross_score": 99999.0,
            "round_index": 99999.0
        },
        {
            "display_name": "\u03a4eam 4 Total",
            "player_id": 99998.0,
            "hole_score_1": 99998.0,
            "hole_score_2": 99998.0,
            "hole_score_3": 99998.0,
            "hole_score_4": 99998.0,
            "hole_score_5": 99998.0,
            "hole_score_6": 99998.0,
            "hole_score_7": 99998.0,
            "hole_score_8": 99998.0,
            "hole_score_9": 99998.0,
            "order_num": 99998.0,
            "spreadsheet_row_num": 99998.0,
            "sex": 99998.0,
            "team_num": 4,
            "tee": 99998.0,
            "captain": 99998.0,
            "hole_scores_array": 99998,
            "net_score": 4.0,
            "hole_score_par_delta_array": 99998,
            "event_info": 99998,
            "rank": 1.0,
            "rank_text": "1st",
            "gross_score": 99998.0,
            "round_index": 99998.0
        },
        {
            "display_name": "\u0392LIND",
            "player_id": 0.0,
            "hole_score_1": 99999.0,
            "hole_score_2": 99999.0,
            "hole_score_3": 99999.0,
            "hole_score_4": 99999.0,
            "hole_score_5": 99999.0,
            "hole_score_6": 99999.0,
            "hole_score_7": 99999.0,
            "hole_score_8": 99999.0,
            "hole_score_9": 99999.0,
            "order_num": 17.0,
            "spreadsheet_row_num": 36.0,
            "sex": 99998.0,
            "team_num": 5,
            "tee": 99998.0,
            "captain": 99998.0,
            "hole_scores_array": [
                0,
                0,
                0,
                0,
                0,
                0,
                0,
                0,
                0
            ],
            "net_score": 1.0,
            "hole_score_par_delta_array": [
                0,
                0,
                0,
                0,
                0,
                0,
                0,
                0,
                0
            ],
            "event_info": {
                "event": "None",
                "hole": 0,
                "display_name": ""
            },
            "rank": "",
            "rank_text": 99998,
            "gross_score": 99999.0,
            "round_index": 99999.0
        },
        {
            "display_name": "\u0392LIND",
            "player_id": 0.0,
            "hole_score_1": 99999.0,
            "hole_score_2": 99999.0,
            "hole_score_3": 99999.0,
            "hole_score_4": 99999.0,
            "hole_score_5": 99999.0,
            "hole_score_6": 99999.0,
            "hole_score_7": 99999.0,
            "hole_score_8": 99999.0,
            "hole_score_9": 99999.0,
            "order_num": 18.0,
            "spreadsheet_row_num": 37.0,
            "sex": 99998.0,
            "team_num": 5,
            "tee": 99998.0,
            "captain": 99998.0,
            "hole_scores_array": [
                0,
                0,
                0,
                0,
                0,
                0,
                0,
                0,
                0
            ],
            "net_score": 1.0,
            "hole_score_par_delta_array": [
                0,
                0,
                0,
                0,
                0,
                0,
                0,
                0,
                0
            ],
            "event_info": {
                "event": "None",
                "hole": 0,
                "display_name": ""
            },
            "rank": "",
            "rank_text": 99998,
            "gross_score": 99999.0,
            "round_index": 99999.0
        },
        {
            "display_name": "\u0392LIND",
            "player_id": 0.0,
            "hole_score_1": 99999.0,
            "hole_score_2": 99999.0,
            "hole_score_3": 99999.0,
            "hole_score_4": 99999.0,
            "hole_score_5": 99999.0,
            "hole_score_6": 99999.0,
            "hole_score_7": 99999.0,
            "hole_score_8": 99999.0,
            "hole_score_9": 99999.0,
            "order_num": 19.0,
            "spreadsheet_row_num": 38.0,
            "sex": 99998.0,
            "team_num": 5,
            "tee": 99998.0,
            "captain": 99998.0,
            "hole_scores_array": [
                0,
                0,
                0,
                0,
                0,
                0,
                0,
                0,
                0
            ],
            "net_score": 1.0,
            "hole_score_par_delta_array": [
                0,
                0,
                0,
                0,
                0,
                0,
                0,
                0,
                0
            ],
            "event_info": {
                "event": "None",
                "hole": 0,
                "display_name": ""
            },
            "rank": "",
            "rank_text": 99998,
            "gross_score": 99999.0,
            "round_index": 99999.0
        },
        {
            "display_name": "\u0392LIND",
            "player_id": 0.0,
            "hole_score_1": 99999.0,
            "hole_score_2": 99999.0,
            "hole_score_3": 99999.0,
            "hole_score_4": 99999.0,
            "hole_score_5": 99999.0,
            "hole_score_6": 99999.0,
            "hole_score_7": 99999.0,
            "hole_score_8": 99999.0,
            "hole_score_9": 99999.0,
            "order_num": 20.0,
            "spreadsheet_row_num": 39.0,
            "sex": 99998.0,
            "team_num": 5,
            "tee": 99998.0,
            "captain": 99998.0,
            "hole_scores_array": [
                0,
                0,
                0,
                0,
                0,
                0,
                0,
                0,
                0
            ],
            "net_score": 1.0,
            "hole_score_par_delta_array": [
                0,
                0,
                0,
                0,
                0,
                0,
                0,
                0,
                0
            ],
            "event_info": {
                "event": "None",
                "hole": 0,
                "display_name": ""
            },
            "rank": "",
            "rank_text": 99998,
            "gross_score": 99999.0,
            "round_index": 99999.0
        },
        {
            "display_name": "\u03a4eam 5 Total",
            "player_id": 99998.0,
            "hole_score_1": 99998.0,
            "hole_score_2": 99998.0,
            "hole_score_3": 99998.0,
            "hole_score_4": 99998.0,
            "hole_score_5": 99998.0,
            "hole_score_6": 99998.0,
            "hole_score_7": 99998.0,
            "hole_score_8": 99998.0,
            "hole_score_9": 99998.0,
            "order_num": 99998.0,
            "spreadsheet_row_num": 99998.0,
            "sex": 99998.0,
            "team_num": 5,
            "tee": 99998.0,
            "captain": 99998.0,
            "hole_scores_array": 99998,
            "net_score": 4.0,
            "hole_score_par_delta_array": 99998,
            "event_info": 99998,
            "rank": 1.0,
            "rank_text": "1st",
            "gross_score": 99998.0,
            "round_index": 99998.0
        },
        {
            "display_name": "\u0392LIND",
            "player_id": 0.0,
            "hole_score_1": 99999.0,
            "hole_score_2": 99999.0,
            "hole_score_3": 99999.0,
            "hole_score_4": 99999.0,
            "hole_score_5": 99999.0,
            "hole_score_6": 99999.0,
            "hole_score_7": 99999.0,
            "hole_score_8": 99999.0,
            "hole_score_9": 99999.0,
            "order_num": 21.0,
            "spreadsheet_row_num": 43.0,
            "sex": 99998.0,
            "team_num": 6,
            "tee": 99998.0,
            "captain": 99998.0,
            "hole_scores_array": [
                0,
                0,
                0,
                0,
                0,
                0,
                0,
                0,
                0
            ],
            "net_score": 1.0,
            "hole_score_par_delta_array": [
                0,
                0,
                0,
                0,
                0,
                0,
                0,
                0,
                0
            ],
            "event_info": {
                "event": "None",
                "hole": 0,
                "display_name": ""
            },
            "rank": "",
            "rank_text": 99998,
            "gross_score": 99999.0,
            "round_index": 99999.0
        },
        {
            "display_name": "\u0392LIND",
            "player_id": 0.0,
            "hole_score_1": 99999.0,
            "hole_score_2": 99999.0,
            "hole_score_3": 99999.0,
            "hole_score_4": 99999.0,
            "hole_score_5": 99999.0,
            "hole_score_6": 99999.0,
            "hole_score_7": 99999.0,
            "hole_score_8": 99999.0,
            "hole_score_9": 99999.0,
            "order_num": 22.0,
            "spreadsheet_row_num": 44.0,
            "sex": 99998.0,
            "team_num": 6,
            "tee": 99998.0,
            "captain": 99998.0,
            "hole_scores_array": [
                0,
                0,
                0,
                0,
                0,
                0,
                0,
                0,
                0
            ],
            "net_score": 1.0,
            "hole_score_par_delta_array": [
                0,
                0,
                0,
                0,
                0,
                0,
                0,
                0,
                0
            ],
            "event_info": {
                "event": "None",
                "hole": 0,
                "display_name": ""
            },
            "rank": "",
            "rank_text": 99998,
            "gross_score": 99999.0,
            "round_index": 99999.0
        },
        {
            "display_name": "\u0392LIND",
            "player_id": 0.0,
            "hole_score_1": 99999.0,
            "hole_score_2": 99999.0,
            "hole_score_3": 99999.0,
            "hole_score_4": 99999.0,
            "hole_score_5": 99999.0,
            "hole_score_6": 99999.0,
            "hole_score_7": 99999.0,
            "hole_score_8": 99999.0,
            "hole_score_9": 99999.0,
            "order_num": 23.0,
            "spreadsheet_row_num": 45.0,
            "sex": 99998.0,
            "team_num": 6,
            "tee": 99998.0,
            "captain": 99998.0,
            "hole_scores_array": [
                0,
                0,
                0,
                0,
                0,
                0,
                0,
                0,
                0
            ],
            "net_score": 1.0,
            "hole_score_par_delta_array": [
                0,
                0,
                0,
                0,
                0,
                0,
                0,
                0,
                0
            ],
            "event_info": {
                "event": "None",
                "hole": 0,
                "display_name": ""
            },
            "rank": "",
            "rank_text": 99998,
            "gross_score": 99999.0,
            "round_index": 99999.0
        },
        {
            "display_name": "\u0392LIND",
            "player_id": 0.0,
            "hole_score_1": 99999.0,
            "hole_score_2": 99999.0,
            "hole_score_3": 99999.0,
            "hole_score_4": 99999.0,
            "hole_score_5": 99999.0,
            "hole_score_6": 99999.0,
            "hole_score_7": 99999.0,
            "hole_score_8": 99999.0,
            "hole_score_9": 99999.0,
            "order_num": 24.0,
            "spreadsheet_row_num": 46.0,
            "sex": 99998.0,
            "team_num": 6,
            "tee": 99998.0,
            "captain": 99998.0,
            "hole_scores_array": [
                0,
                0,
                0,
                0,
                0,
                0,
                0,
                0,
                0
            ],
            "net_score": 1.0,
            "hole_score_par_delta_array": [
                0,
                0,
                0,
                0,
                0,
                0,
                0,
                0,
                0
            ],
            "event_info": {
                "event": "None",
                "hole": 0,
                "display_name": ""
            },
            "rank": "",
            "rank_text": 99998,
            "gross_score": 99999.0,
            "round_index": 99999.0
        },
        {
            "display_name": "\u03a4eam 6 Total",
            "player_id": 99998.0,
            "hole_score_1": 99998.0,
            "hole_score_2": 99998.0,
            "hole_score_3": 99998.0,
            "hole_score_4": 99998.0,
            "hole_score_5": 99998.0,
            "hole_score_6": 99998.0,
            "hole_score_7": 99998.0,
            "hole_score_8": 99998.0,
            "hole_score_9": 99998.0,
            "order_num": 99998.0,
            "spreadsheet_row_num": 99998.0,
            "sex": 99998.0,
            "team_num": 6,
            "tee": 99998.0,
            "captain": 99998.0,
            "hole_scores_array": 99998,
            "net_score": 4.0,
            "hole_score_par_delta_array": 99998,
            "event_info": 99998,
            "rank": 1.0,
            "rank_text": "1st",
            "gross_score": 99998.0,
            "round_index": 99998.0
        },
        {
            "display_name": "\u0392LIND",
            "player_id": 0.0,
            "hole_score_1": 99999.0,
            "hole_score_2": 99999.0,
            "hole_score_3": 99999.0,
            "hole_score_4": 99999.0,
            "hole_score_5": 99999.0,
            "hole_score_6": 99999.0,
            "hole_score_7": 99999.0,
            "hole_score_8": 99999.0,
            "hole_score_9": 99999.0,
            "order_num": 25.0,
            "spreadsheet_row_num": 50.0,
            "sex": 99998.0,
            "team_num": 7,
            "tee": 99998.0,
            "captain": 99998.0,
            "hole_scores_array": [
                0,
                0,
                0,
                0,
                0,
                0,
                0,
                0,
                0
            ],
            "net_score": 1.0,
            "hole_score_par_delta_array": [
                0,
                0,
                0,
                0,
                0,
                0,
                0,
                0,
                0
            ],
            "event_info": {
                "event": "None",
                "hole": 0,
                "display_name": ""
            },
            "rank": "",
            "rank_text": 99998,
            "gross_score": 99999.0,
            "round_index": 99999.0
        },
        {
            "display_name": "\u0392LIND",
            "player_id": 0.0,
            "hole_score_1": 99999.0,
            "hole_score_2": 99999.0,
            "hole_score_3": 99999.0,
            "hole_score_4": 99999.0,
            "hole_score_5": 99999.0,
            "hole_score_6": 99999.0,
            "hole_score_7": 99999.0,
            "hole_score_8": 99999.0,
            "hole_score_9": 99999.0,
            "order_num": 26.0,
            "spreadsheet_row_num": 51.0,
            "sex": 99998.0,
            "team_num": 7,
            "tee": 99998.0,
            "captain": 99998.0,
            "hole_scores_array": [
                0,
                0,
                0,
                0,
                0,
                0,
                0,
                0,
                0
            ],
            "net_score": 1.0,
            "hole_score_par_delta_array": [
                0,
                0,
                0,
                0,
                0,
                0,
                0,
                0,
                0
            ],
            "event_info": {
                "event": "None",
                "hole": 0,
                "display_name": ""
            },
            "rank": "",
            "rank_text": 99998,
            "gross_score": 99999.0,
            "round_index": 99999.0
        },
        {
            "display_name": "\u0392LIND",
            "player_id": 0.0,
            "hole_score_1": 99999.0,
            "hole_score_2": 99999.0,
            "hole_score_3": 99999.0,
            "hole_score_4": 99999.0,
            "hole_score_5": 99999.0,
            "hole_score_6": 99999.0,
            "hole_score_7": 99999.0,
            "hole_score_8": 99999.0,
            "hole_score_9": 99999.0,
            "order_num": 27.0,
            "spreadsheet_row_num": 52.0,
            "sex": 99998.0,
            "team_num": 7,
            "tee": 99998.0,
            "captain": 99998.0,
            "hole_scores_array": [
                0,
                0,
                0,
                0,
                0,
                0,
                0,
                0,
                0
            ],
            "net_score": 1.0,
            "hole_score_par_delta_array": [
                0,
                0,
                0,
                0,
                0,
                0,
                0,
                0,
                0
            ],
            "event_info": {
                "event": "None",
                "hole": 0,
                "display_name": ""
            },
            "rank": "",
            "rank_text": 99998,
            "gross_score": 99999.0,
            "round_index": 99999.0
        },
        {
            "display_name": "\u0392LIND",
            "player_id": 0.0,
            "hole_score_1": 99999.0,
            "hole_score_2": 99999.0,
            "hole_score_3": 99999.0,
            "hole_score_4": 99999.0,
            "hole_score_5": 99999.0,
            "hole_score_6": 99999.0,
            "hole_score_7": 99999.0,
            "hole_score_8": 99999.0,
            "hole_score_9": 99999.0,
            "order_num": 28.0,
            "spreadsheet_row_num": 53.0,
            "sex": 99998.0,
            "team_num": 7,
            "tee": 99998.0,
            "captain": 99998.0,
            "hole_scores_array": [
                0,
                0,
                0,
                0,
                0,
                0,
                0,
                0,
                0
            ],
            "net_score": 1.0,
            "hole_score_par_delta_array": [
                0,
                0,
                0,
                0,
                0,
                0,
                0,
                0,
                0
            ],
            "event_info": {
                "event": "None",
                "hole": 0,
                "display_name": ""
            },
            "rank": "",
            "rank_text": 99998,
            "gross_score": 99999.0,
            "round_index": 99999.0
        },
        {
            "display_name": "\u03a4eam 7 Total",
            "player_id": 99998.0,
            "hole_score_1": 99998.0,
            "hole_score_2": 99998.0,
            "hole_score_3": 99998.0,
            "hole_score_4": 99998.0,
            "hole_score_5": 99998.0,
            "hole_score_6": 99998.0,
            "hole_score_7": 99998.0,
            "hole_score_8": 99998.0,
            "hole_score_9": 99998.0,
            "order_num": 99998.0,
            "spreadsheet_row_num": 99998.0,
            "sex": 99998.0,
            "team_num": 7,
            "tee": 99998.0,
            "captain": 99998.0,
            "hole_scores_array": 99998,
            "net_score": 4.0,
            "hole_score_par_delta_array": 99998,
            "event_info": 99998,
            "rank": 1.0,
            "rank_text": "1st",
            "gross_score": 99998.0,
            "round_index": 99998.0
        },
        {
            "display_name": "\u0392LIND",
            "player_id": 0.0,
            "hole_score_1": 99999.0,
            "hole_score_2": 99999.0,
            "hole_score_3": 99999.0,
            "hole_score_4": 99999.0,
            "hole_score_5": 99999.0,
            "hole_score_6": 99999.0,
            "hole_score_7": 99999.0,
            "hole_score_8": 99999.0,
            "hole_score_9": 99999.0,
            "order_num": 29.0,
            "spreadsheet_row_num": 57.0,
            "sex": 99998.0,
            "team_num": 8,
            "tee": 99998.0,
            "captain": 99998.0,
            "hole_scores_array": [
                0,
                0,
                0,
                0,
                0,
                0,
                0,
                0,
                0
            ],
            "net_score": 1.0,
            "hole_score_par_delta_array": [
                0,
                0,
                0,
                0,
                0,
                0,
                0,
                0,
                0
            ],
            "event_info": {
                "event": "None",
                "hole": 0,
                "display_name": ""
            },
            "rank": "",
            "rank_text": 99998,
            "gross_score": 99999.0,
            "round_index": 99999.0
        },
        {
            "display_name": "\u0392LIND",
            "player_id": 0.0,
            "hole_score_1": 99999.0,
            "hole_score_2": 99999.0,
            "hole_score_3": 99999.0,
            "hole_score_4": 99999.0,
            "hole_score_5": 99999.0,
            "hole_score_6": 99999.0,
            "hole_score_7": 99999.0,
            "hole_score_8": 99999.0,
            "hole_score_9": 99999.0,
            "order_num": 30.0,
            "spreadsheet_row_num": 58.0,
            "sex": 99998.0,
            "team_num": 8,
            "tee": 99998.0,
            "captain": 99998.0,
            "hole_scores_array": [
                0,
                0,
                0,
                0,
                0,
                0,
                0,
                0,
                0
            ],
            "net_score": 1.0,
            "hole_score_par_delta_array": [
                0,
                0,
                0,
                0,
                0,
                0,
                0,
                0,
                0
            ],
            "event_info": {
                "event": "None",
                "hole": 0,
                "display_name": ""
            },
            "rank": "",
            "rank_text": 99998,
            "gross_score": 99999.0,
            "round_index": 99999.0
        },
        {
            "display_name": "\u0392LIND",
            "player_id": 0.0,
            "hole_score_1": 99999.0,
            "hole_score_2": 99999.0,
            "hole_score_3": 99999.0,
            "hole_score_4": 99999.0,
            "hole_score_5": 99999.0,
            "hole_score_6": 99999.0,
            "hole_score_7": 99999.0,
            "hole_score_8": 99999.0,
            "hole_score_9": 99999.0,
            "order_num": 31.0,
            "spreadsheet_row_num": 59.0,
            "sex": 99998.0,
            "team_num": 8,
            "tee": 99998.0,
            "captain": 99998.0,
            "hole_scores_array": [
                0,
                0,
                0,
                0,
                0,
                0,
                0,
                0,
                0
            ],
            "net_score": 1.0,
            "hole_score_par_delta_array": [
                0,
                0,
                0,
                0,
                0,
                0,
                0,
                0,
                0
            ],
            "event_info": {
                "event": "None",
                "hole": 0,
                "display_name": ""
            },
            "rank": "",
            "rank_text": 99998,
            "gross_score": 99999.0,
            "round_index": 99999.0
        },
        {
            "display_name": "\u0392LIND",
            "player_id": 0.0,
            "hole_score_1": 99999.0,
            "hole_score_2": 99999.0,
            "hole_score_3": 99999.0,
            "hole_score_4": 99999.0,
            "hole_score_5": 99999.0,
            "hole_score_6": 99999.0,
            "hole_score_7": 99999.0,
            "hole_score_8": 99999.0,
            "hole_score_9": 99999.0,
            "order_num": 32.0,
            "spreadsheet_row_num": 60.0,
            "sex": 99998.0,
            "team_num": 8,
            "tee": 99998.0,
            "captain": 99998.0,
            "hole_scores_array": [
                0,
                0,
                0,
                0,
                0,
                0,
                0,
                0,
                0
            ],
            "net_score": 1.0,
            "hole_score_par_delta_array": [
                0,
                0,
                0,
                0,
                0,
                0,
                0,
                0,
                0
            ],
            "event_info": {
                "event": "None",
                "hole": 0,
                "display_name": ""
            },
            "rank": "",
            "rank_text": 99998,
            "gross_score": 99999.0,
            "round_index": 99999.0
        },
        {
            "display_name": "\u03a4eam 8 Total",
            "player_id": 99998.0,
            "hole_score_1": 99998.0,
            "hole_score_2": 99998.0,
            "hole_score_3": 99998.0,
            "hole_score_4": 99998.0,
            "hole_score_5": 99998.0,
            "hole_score_6": 99998.0,
            "hole_score_7": 99998.0,
            "hole_score_8": 99998.0,
            "hole_score_9": 99998.0,
            "order_num": 99998.0,
            "spreadsheet_row_num": 99998.0,
            "sex": 99998.0,
            "team_num": 8,
            "tee": 99998.0,
            "captain": 99998.0,
            "hole_scores_array": 99998,
            "net_score": 4.0,
            "hole_score_par_delta_array": 99998,
            "event_info": 99998,
            "rank": 1.0,
            "rank_text": "1st",
            "gross_score": 99998.0,
            "round_index": 99998.0
        },
        {
            "display_name": "\u03a9 Average",
            "player_id": 99998.0,
            "hole_score_1": 99998.0,
            "hole_score_2": 99998.0,
            "hole_score_3": 99998.0,
            "hole_score_4": 99998.0,
            "hole_score_5": 99998.0,
            "hole_score_6": 99998.0,
            "hole_score_7": 99998.0,
            "hole_score_8": 99998.0,
            "hole_score_9": 99998.0,
            "order_num": 16.5,
            "spreadsheet_row_num": 34.0,
            "sex": 99998.0,
            "team_num": 99998,
            "tee": 99998.0,
            "captain": 99998.0,
            "hole_scores_array": 99998,
            "net_score": 1.0,
            "hole_score_par_delta_array": 99998,
            "event_info": 99998,
            "rank": "",
            "rank_text": 99998,
            "gross_score": 99998.0,
            "round_index": 99998.0
        }
    ]
}